videoscope/__init__.py
videoscope/ffmpeg_video_handler.py
videoscope/metadata_extractor.py
videoscope/opencv_thumbnail_generator.py
videoscope/video_info.py
videoscope/config/__init__.py
videoscope/config/timecode.py
videoscope/errors/__init__.py
videoscope/errors/file_handle_errors.py
videoscope/errors/timecode_errors.py
videoscope/errors/video_info_errors.py
videoscope/interfaces/__init__.py
videoscope/interfaces/i_thumbnail_generator.py
videoscope/interfaces/i_video_handler.py
videoscope/interfaces/i_video_metadata_extractor.py
videoscope/models/__init__.py
videoscope/models/format_metadata.py
videoscope/models/metadata.py
videoscope/models/timecode.py
gh_video_scope-1.0.1.dist-info/LICENSE
gh_video_scope-1.0.1.dist-info/LICENSE.md
gh_video_scope-1.0.1.dist-info/METADATA
gh_video_scope-1.0.1.dist-info/WHEEL
gh_video_scope-1.0.1.dist-info/entry_points.txt
gh_video_scope-1.0.1.dist-info/top_level.txt
gh_video_scope-1.0.1.dist-info/RECORD
