Metadata-Version: 2.1
Name: gh-video-scope
Version: 1.0.1
Summary: Package for extracting metadata from video files
Home-page: https://github.com/m-ghiani/VideoScope
Author: Massimo Ghiani
Author-email: m.ghiani@gmail.com
License: MIT
Classifier: Development Status :: 5 - Production/Stable
Classifier: Intended Audience :: Developers
Classifier: License :: OSI Approved :: MIT License
Classifier: Programming Language :: Python :: 3
Classifier: Programming Language :: Python :: 3.6
Classifier: Programming Language :: Python :: 3.7
Classifier: Programming Language :: Python :: 3.8
Classifier: Programming Language :: Python :: 3.9
Classifier: Programming Language :: Python :: 3.10
Classifier: Programming Language :: Python :: 3.11
Classifier: Programming Language :: Python :: 3.12
Requires-Python: >=3.10
License-File: LICENSE
License-File: LICENSE.md
Requires-Dist: ffmpeg-python
Requires-Dist: future
Requires-Dist: numpy
Requires-Dist: opencv-python
